{"libaccess.so":1132814,"libadl.so":1313600,"libagi.so":1804831,"libagos.so":2193505,"libags.so":15691981,"libalg.so":2152593,"libasylum.so":2605366,"libavalanche.so":1230828,"libbagel.so":3241829,"libbbvs.so":656188,"libbladerunner.so":6619646,"libburied.so":2212930,"libcge.so":529270,"libcge2.so":539376,"libchamber.so":864740,"libchewy.so":1474868,"libcine.so":1313273,"libcomposer.so":533628,"libcrab.so":2833171,"libcruise.so":1136289,"libcryo.so":733791,"libcryomni3d.so":2070960,"libdarkseed.so":1126320,"libdgds.so":2680509,"libdirector.so":10220362,"libdm.so":1170486,"libdraci.so":596991,"libdragons.so":1132815,"libdrascula.so":814863,"libdreamweb.so":934639,"libefh.so":809087,"libfreescape.so":2705150,"libglk.so":14807644,"libgnap.so":1474954,"libgob.so":4318185,"libgot.so":1049950,"libgriffon.so":699812,"libgrim.so":4572621,"libgroovie.so":1143118,"libhadesch.so":3687568,"libhdb.so":1742629,"libhopkins.so":1593954,"libhugo.so":918869,"libhypno.so":2749692,"libicb.so":7811568,"libillusions.so":1675563,"libimmortal.so":368194,"libkingdom.so":558298,"libkyra.so":11024540,"liblab.so":626205,"liblastexpress.so":7141930,"liblilliput.so":559748,"liblure.so":1355864,"libm4.so":8376242,"libmacventure.so":667414,"libmade.so":603400,"libmads.so":9301572,"libmediastation.so":688567,"libmm.so":8352909,"libmohawk.so":4525585,"libmortevielle.so":644548,"libmtropolis.so":7245083,"libmutationofjb.so":788152,"libmyst3.so":2177787,"libnancy.so":4457975,"libneverhood.so":3693025,"libngi.so":2525452,"libparallaction.so":1798646,"libpegasus.so":3356352,"libpetka.so":703186,"libpink.so":819208,"libplayground3d.so":130994,"libplumbers.so":145059,"libprince.so":974476,"libprivate.so":545429,"libqdengine.so":4567970,"libqueen.so":959263,"libsaga.so":2018578,"libsaga2.so":4184775,"libsci.so":8706368,"libscumm.so":12511454,"libsherlock.so":3219088,"libsky.so":718440,"libsludge.so":872466,"libstark.so":3444399,"libstartrek.so":2993229,"libsupernova.so":1421690,"libsword1.so":1051913,"libsword2.so":1114742,"libsword25.so":1415972,"libteenagent.so":820253,"libtestbed.so":782012,"libtetraedge.so":5885106,"libtinsel.so":2583733,"libtitanic.so":8647447,"libtoltecs.so":597054,"libtony.so":2549991,"libtoon.so":1116348,"libtouche.so":624489,"libtrecision.so":1006594,"libtsage.so":11633489,"libtucker.so":637553,"libtwine.so":1999584,"libtwp.so":4906283,"libultima.so":14349909,"libvcruise.so":2112202,"libvoyeur.so":637186,"libwage.so":561755,"libwintermute.so":5556713,"libzvision.so":1349245}